dict2json/__init__.py
dict2json-0.1.2.dist-info/LICENSE
dict2json-0.1.2.dist-info/METADATA
dict2json-0.1.2.dist-info/WHEEL
dict2json-0.1.2.dist-info/entry_points.txt
dict2json-0.1.2.dist-info/top_level.txt
dict2json-0.1.2.dist-info/RECORD
